minchin/text.py
minchin_text-7.0.0.dist-info/licenses/LICENSE
minchin_text-7.0.0.dist-info/METADATA
minchin_text-7.0.0.dist-info/WHEEL
minchin_text-7.0.0.dist-info/top_level.txt
minchin_text-7.0.0.dist-info/RECORD
