Metadata-Version: 2.4
Name: minchin.text
Version: 7.0.0
Summary: Python library for text formatting on the command line.
Author-email: William Minchin <w_minchin@hotmail.com>
Maintainer-email: William Minchin <w_minchin@hotmail.com>
License-Expression: MIT
Project-URL: Bug Tracker, https://github.com/minchinweb/minchin.text/issues
Project-URL: Repository, https://github.com/minchinweb/minchin.text
Project-URL: Changelog, https://github.com/minchinweb/minchin.text/blob/master/CHANGELOG.rst
Classifier: Development Status :: 5 - Production/Stable
Classifier: Environment :: Console
Classifier: Programming Language :: Python :: 2.6
Classifier: Programming Language :: Python :: 2.7
Classifier: Programming Language :: Python :: 3
Classifier: Programming Language :: Python :: 3.2
Classifier: Programming Language :: Python :: 3.3
Classifier: Programming Language :: Python :: 3.4
Classifier: Programming Language :: Python :: 3.5
Classifier: Programming Language :: Python :: 3.6
Classifier: Programming Language :: Python :: 3.7
Classifier: Programming Language :: Python :: 3.8
Classifier: Programming Language :: Python :: 3.9
Classifier: Programming Language :: Python :: 3.10
Classifier: Programming Language :: Python :: 3.11
Classifier: Programming Language :: Python :: 3.12
Classifier: Programming Language :: Python :: 3.13
Classifier: Natural Language :: English
Classifier: Intended Audience :: Developers
Classifier: Operating System :: OS Independent
Classifier: Topic :: Utilities
Classifier: Topic :: Software Development :: Libraries :: Python Modules
License-File: LICENSE
Requires-Dist: colorama>=0.2.5
Requires-Dist: backports.shutil_get_terminal_size>=1.0.0; python_version == "2.6"
Requires-Dist: backports.shutil_get_terminal_size>=1.0.0; python_version == "2.7"
Requires-Dist: backports.shutil_get_terminal_size>=1.0.0; python_version == "3.2"
Provides-Extra: build
Requires-Dist: minchin.releaser>=0.8.2; extra == "build"
Provides-Extra: docs
Provides-Extra: test
Provides-Extra: dev
Requires-Dist: black; extra == "dev"
Dynamic: license-file
